Workbook

Sheet Hoja1
D1: SINDICATO ÚNICO DE TRABAJADORES DE LA INDUSTRIA LÁCTEA ALIMENTICIA,
D2: SIMILARES Y CONEXOS DE LA REPÚBLICA MEXICANA SECCIÓN COATEPEC
D3: Tarjetas de Caja de Ahorro y Préstamos
F4: Ejercicio
B6: NÚMERO | F6: CATEGORÍA | J6: VALOR DE ACCIÓN
B8: NOMBRE | I8: INTERÉS MENSUAL
B9: SEM | C9: FECHA | D9: AHORRO | E9: ABONO | F9: PRÉSTAMO | G9: MESES | H9: =I7 -> 0 | I9: SALDO | J9: SALDO | K9: COSTO
H10: INTERÉS | I10: A CARGO | J10: A FAVOR | K10: RECIBOS
B11: 50 | D11: 0 | E11: 0 | F11: 0 | G11: 0 | H11: 0 | I11: 0 | J11: 0 | K11: 0
B12: 51 | D12: 0 | E12: 0 | F12: 0 | G12: 0 | H12: 0 | I12: 0 | J12: 0 | K12: 0
B13: 52 | D13: 0 | E13: 0 | F13: 0 | G13: 0 | H13: 0 | I13: 0 | J13: 0 | K13: 0
B14: 1 | D14: 0 | E14: 0 | F14: 0 | G14: 0 | H14: 0 | I14: 0 | J14: 0 | K14: 0
B15: 2 | D15: 0 | E15: 0 | F15: 0 | G15: 0 | H15: 0 | I15: 0 | J15: 0 | K15: 0
B16: 3 | D16: 0 | E16: 0 | F16: 0 | G16: 0 | H16: 0 | I16: 0 | J16: 0 | K16: 0
B17: 4 | D17: 0 | E17: 0 | F17: 0 | G17: 0 | H17: 0 | I17: 0 | J17: 0 | K17: 0
B18: 5 | D18: 0 | E18: 0 | F18: 0 | G18: 0 | H18: 0 | I18: 0 | J18: 0 | K18: 0
B19: 6 | D19: 0 | E19: 0 | F19: 0 | G19: 0 | H19: 0 | I19: 0 | J19: 0 | K19: 0
B20: 7 | D20: 0 | E20: 0 | F20: 0 | G20: 0 | H20: 0 | I20: 0 | J20: 0 | K20: 0
B21: 8 | D21: 0 | E21: 0 | F21: 0 | G21: 0 | H21: 0 | I21: 0 | J21: 0 | K21: 0
B22: 9 | D22: 0 | E22: 0 | F22: 0 | G22: 0 | H22: 0 | I22: 0 | J22: 0 | K22: 0
... B62: 49 | D62: 0 | E62: 0 | F62: 0 | G62: 0 | H62: 0 | I62: 0 | J62: 0 | K62: 0
D63: =SUM(D11:D62) -> 0 | E63: =SUM(E11:E62) -> 0 | F63: =SUM(F11:F62) -> 0 | H63: =SUM(H11:H62) -> 0 | I63: =IF((D63+E63-F63-H63-K63)<0,(D63+E63-F63-H63-K63),0) -> 0 | J63: =IF((D63+E63-F63-H63-K63)>0,D63+E63-F63-H63-K63,0) -> 0 | K63: =SUM(K11:K62) -> 0
B68: FIRMA DE CONFORMIDAD

Sheet Hoja 2
D1: SINDICATO ÚNICO DE TRABAJADORES DE LA INDUSTRIA LÁCTEA ALIMENTICIA,
D2: SIMILARES Y CONEXOS DE LA REPÚBLICA MEXICANA SECCIÓN COATEPEC
D3: Tarjetas de Caja de Ahorro y Préstamos
F4: Ejercicio | G4: =Hoja1!G4 -> 0
B5: =Hoja1!B5 -> 0 | F5: =Hoja1!F5 -> 0 | J5: =Hoja1!J5 -> 0
B6: NÚMERO | F6: CATEGORÍA | J6: VALOR DE ACCIÓN
B7: =Hoja1!B7 -> 0 | I7: =Hoja1!I7 -> 0
B8: NOMBRE | I8: INTERÉS MENSUAL
D15: VALOR DE LA ACCION | I15: =J5 -> 0
D18: AHORRO | I18: =Hoja1!D63 -> 0
D21: ABONO | I21: =Hoja1!E63 -> 0
D24: TOTAL DE PAGOS | I24: =SUM(I15,I18,I21) -> 0
D28: PRESTAMO | I28: =Hoja1!F63 -> 0
D31: INTERESES COBRADO | I31: =Hoja1!H63 -> 0
D34: RECIBO | I34: =Hoja1!K63 -> 0
D37: COBRO VALOR DE ACCION | I37: =J5 -> 0
D40: TOTAL DE COBROS | I40: =SUM(I28,I31,I34,I37) -> 0
D44: SALDO A FAVOR | I44: =I24-I40 -> 0
D48: INETERSES A REPARTIR
D52: SALDO TOTAL A FAVOR | I52: =I44+I48 -> 0
B68: FIRMA DE CONFORMIDAD
